[
 {
  "Asin": "B088LTC2MM",
  "URL": "https://www.amazon.co.jp/dp/B088LTC2MM?tag=99hatena-22&linkCode=ogi&th=1&psc=1",
  "ImageURL": "https://m.media-amazon.com/images/I/612VAL2tiqL.jpg",
  "Publisher": "竹書房",
  "Contributor": "華藤りえ(著)",
  "Booktype": "Kindle版",
  "Title": "騎士団長とえっちしたら、甘い新婚生活が始まりました！ (蜜猫文庫)",
  "Price": 436,
  "Category": "ジャンル別,ライトノベル",
  "Points": 4
 },
 {
  "Asin": "B087332NDW",
  "URL": "https://www.amazon.co.jp/dp/B087332NDW?tag=99hatena-22&linkCode=ogi&th=1&psc=1",
  "ImageURL": "https://m.media-amazon.com/images/I/51O0cC22bYL.jpg",
  "Publisher": "竹書房",
  "Contributor": "青砥あか(著)",
  "Booktype": "Kindle版",
  "Title": "激甘ドS外科医に脅迫溺愛されてます (蜜夢文庫)",
  "Price": 413,
  "Category": "ジャンル別,ライトノベル",
  "Points": 4
 },
 {
  "Asin": "B083W9TQTZ",
  "URL": "https://www.amazon.co.jp/dp/B083W9TQTZ?tag=99hatena-22&linkCode=ogi&th=1&psc=1",
  "ImageURL": "https://m.media-amazon.com/images/I/61-+l41d4SL.jpg",
  "Publisher": "竹書房",
  "Contributor": "花菱ななみ(著)",
  "Booktype": "Kindle版",
  "Title": "悪役令嬢に転生したけど、破局したはずのカタブツ王太子に溺愛されてます！？ (蜜猫文庫)",
  "Price": 438,
  "Category": "ジャンル別,ライトノベル",
  "Points": 4
 },
 {
  "Asin": "B085W24HW2",
  "URL": "https://www.amazon.co.jp/dp/B085W24HW2?tag=99hatena-22&linkCode=ogi&th=1&psc=1",
  "ImageURL": "https://m.media-amazon.com/images/I/51fSj1L3UwL.jpg",
  "Publisher": "竹書房",
  "Contributor": "伽月るーこ(著)",
  "Booktype": "Kindle版",
  "Title": "国王陛下と秘密の恋　暗がりでとろけるような口づけを (蜜猫文庫)",
  "Price": 438,
  "Category": "ジャンル別,ライトノベル",
  "Points": 4
 },
 {
  "Asin": "B088LM22HD",
  "URL": "https://www.amazon.co.jp/dp/B088LM22HD?tag=99hatena-22&linkCode=ogi&th=1&psc=1",
  "ImageURL": "https://m.media-amazon.com/images/I/51LtvsKvCML.jpg",
  "Publisher": "竹書房",
  "Contributor": "御影りさ(著)",
  "Booktype": "Kindle版",
  "Title": "ヤンデレ系乙女ゲームの悪役令嬢に転生したので、推しを監禁しています。 (ムーンドロップス)",
  "Price": 436,
  "Category": "ジャンル別,ライトノベル",
  "Points": 4
 },
 {
  "Asin": "B088LRNDHP",
  "URL": "https://www.amazon.co.jp/dp/B088LRNDHP?tag=99hatena-22&linkCode=ogi&th=1&psc=1",
  "ImageURL": "https://m.media-amazon.com/images/I/61X9-eL8h9L.jpg",
  "Publisher": "竹書房",
  "Contributor": "春日部こみと(著)",
  "Booktype": "Kindle版",
  "Title": "転生伯爵令嬢は麗しの騎士に執愛される　今度こそは幸せになります (蜜猫文庫)",
  "Price": 436,
  "Category": "ジャンル別,ライトノベル",
  "Points": 4
 },
 {
  "Asin": "B083W9ZC5C",
  "URL": "https://www.amazon.co.jp/dp/B083W9ZC5C?tag=99hatena-22&linkCode=ogi&th=1&psc=1",
  "ImageURL": "https://m.media-amazon.com/images/I/61c7BoBtKvL.jpg",
  "Publisher": "竹書房",
  "Contributor": "クレイン(著)",
  "Booktype": "Kindle版",
  "Title": "仔猫な花嫁は我慢しない 公爵閣下の溺愛教育 (蜜猫文庫)",
  "Price": 436,
  "Category": "ジャンル別,ライトノベル",
  "Points": 4
 },
 {
  "Asin": "B07WFMQQ65",
  "URL": "https://www.amazon.co.jp/dp/B07WFMQQ65?tag=99hatena-22&linkCode=ogi&th=1&psc=1",
  "ImageURL": "https://m.media-amazon.com/images/I/51eOg2BiUWL.jpg",
  "Publisher": "竹書房",
  "Contributor": "クレイン(著)",
  "Booktype": "Kindle版",
  "Title": "婚約者を略奪されたら、腹黒策士に熱烈に求愛されています！！ (蜜猫ｎｏｖｅｌｓ)",
  "Price": 708,
  "Category": "ジャンル別,ライトノベル",
  "Points": 7
 },
 {
  "Asin": "B07CHC4BBT",
  "URL": "https://www.amazon.co.jp/dp/B07CHC4BBT?tag=99hatena-22&linkCode=ogi&th=1&psc=1",
  "ImageURL": "https://m.media-amazon.com/images/I/61P1HGPeG3L.jpg",
  "Publisher": "竹書房",
  "Contributor": "山野辺りり(著)",
  "Booktype": "Kindle版",
  "Title": "侯爵令息は意地っ張りな令嬢をかわいがりたくて仕方ない (蜜猫文庫)",
  "Price": 397,
  "Category": "ジャンル別,ライトノベル",
  "Points": 4
 },
 {
  "Asin": "B085W2FN7Z",
  "URL": "https://www.amazon.co.jp/dp/B085W2FN7Z?tag=99hatena-22&linkCode=ogi&th=1&psc=1",
  "ImageURL": "https://m.media-amazon.com/images/I/517tcLf4NHL.jpg",
  "Publisher": "竹書房",
  "Contributor": "すずね凜(著)",
  "Booktype": "Kindle版",
  "Title": "没落令嬢は不眠皇帝陛下の抱き枕になりまして (蜜猫文庫)",
  "Price": 438,
  "Category": "ジャンル別,ライトノベル",
  "Points": 4
 },
 {
  "Asin": "B07T3C2HRJ",
  "URL": "https://www.amazon.co.jp/dp/B07T3C2HRJ?tag=99hatena-22&linkCode=ogi&th=1&psc=1",
  "ImageURL": "https://m.media-amazon.com/images/I/51exvKQEHLL.jpg",
  "Publisher": "竹書房",
  "Contributor": "兎山もなか(著)",
  "Booktype": "Kindle版",
  "Title": "清く正しくいやらしく　まじめOLのビッチ宣言 (蜜夢文庫)",
  "Price": 436,
  "Category": "ジャンル別,ライトノベル",
  "Points": 4
 },
 {
  "Asin": "B07KG4XC7R",
  "URL": "https://www.amazon.co.jp/dp/B07KG4XC7R?tag=99hatena-22&linkCode=ogi&th=1&psc=1",
  "ImageURL": "https://m.media-amazon.com/images/I/51XB7WgdeNL.jpg",
  "Publisher": "竹書房",
  "Contributor": "葉月クロル(著)",
  "Booktype": "Kindle版",
  "Title": "異世界の恋人はスライム王子の触手で溺愛される (ムーンドロップス)",
  "Price": 770,
  "Category": "ジャンル別,ライトノベル",
  "Points": 8
 },
 {
  "Asin": "B079Y3GR85",
  "URL": "https://www.amazon.co.jp/dp/B079Y3GR85?tag=99hatena-22&linkCode=ogi&th=1&psc=1",
  "ImageURL": "https://m.media-amazon.com/images/I/61OwIP-XbAL.jpg",
  "Publisher": "竹書房",
  "Contributor": "葉月エリカ(著)",
  "Booktype": "Kindle版",
  "Title": "人間不信な王子様に嫁いだら、執着ワンコと化して懐かれました (蜜猫文庫)",
  "Price": 397,
  "Category": "ジャンル別,ライトノベル",
  "Points": 4
 },
 {
  "Asin": "B07SZ45C5N",
  "URL": "https://www.amazon.co.jp/dp/B07SZ45C5N?tag=99hatena-22&linkCode=ogi&th=1&psc=1",
  "ImageURL": "https://m.media-amazon.com/images/I/51krWlLTI3L.jpg",
  "Publisher": "竹書房",
  "Contributor": "百均(著)",
  "Booktype": "Kindle版",
  "Title": "悪魔に騙されてＴＳ転生したけどめげずにハーレム目指します１ (ヴァリアントノベルズ)",
  "Price": 599,
  "Category": "ジャンル別,ライトノベル",
  "Points": 6
 },
 {
  "Asin": "B07KG3TWWC",
  "URL": "https://www.amazon.co.jp/dp/B07KG3TWWC?tag=99hatena-22&linkCode=ogi&th=1&psc=1",
  "ImageURL": "https://m.media-amazon.com/images/I/51IMyi-K1NL.jpg",
  "Publisher": "竹書房",
  "Contributor": "みかづき紅月(著)",
  "Booktype": "Kindle版",
  "Title": "富豪紳士の危険な溺愛　昼下がりの淫らな診察 (蜜猫文庫)",
  "Price": 397,
  "Category": "ジャンル別,ライトノベル",
  "Points": 4
 },
 {
  "Asin": "B07QL5J1DW",
  "URL": "https://www.amazon.co.jp/dp/B07QL5J1DW?tag=99hatena-22&linkCode=ogi&th=1&psc=1",
  "ImageURL": "https://m.media-amazon.com/images/I/51ZTRlfdNhL.jpg",
  "Publisher": "竹書房",
  "Contributor": "華藤りえ(著)",
  "Booktype": "Kindle版",
  "Title": "人生がリセットされたら新婚溺愛幸せシナリオに変更されました (蜜猫ｎｏｖｅｌｓ)",
  "Price": 708,
  "Category": "ジャンル別,ライトノベル",
  "Points": 7
 },
 {
  "Asin": "B07PQJ63WJ",
  "URL": "https://www.amazon.co.jp/dp/B07PQJ63WJ?tag=99hatena-22&linkCode=ogi&th=1&psc=1",
  "ImageURL": "https://m.media-amazon.com/images/I/51hydZCe1YL.jpg",
  "Publisher": "竹書房",
  "Contributor": "御堂志生(著)",
  "Booktype": "Kindle版",
  "Title": "国王陛下は最愛の令嬢と息子に癒やされたい (蜜猫文庫)",
  "Price": 413,
  "Category": "ジャンル別,ライトノベル",
  "Points": 4
 },
 {
  "Asin": "B07WGLNCRR",
  "URL": "https://www.amazon.co.jp/dp/B07WGLNCRR?tag=99hatena-22&linkCode=ogi&th=1&psc=1",
  "ImageURL": "https://m.media-amazon.com/images/I/51KtoW4t76L.jpg",
  "Publisher": "竹書房",
  "Contributor": "天ヶ森雀(著)",
  "Booktype": "Kindle版",
  "Title": "アラサー女子と多忙な王子様のオトナな関係 (蜜夢文庫)",
  "Price": 440,
  "Category": "ジャンル別,ライトノベル",
  "Points": 4
 },
 {
  "Asin": "B074M3QN6P",
  "URL": "https://www.amazon.co.jp/dp/B074M3QN6P?tag=99hatena-22&linkCode=ogi&th=1&psc=1",
  "ImageURL": "https://m.media-amazon.com/images/I/61pDQAhVI3L.jpg",
  "Publisher": "竹書房",
  "Contributor": "当麻咲来(著)",
  "Booktype": "Kindle版",
  "Title": "王立魔法図書館の［錠前］に転職することになりまして 王立魔法図書館シリーズ (ムーンドロップス)",
  "Price": 660,
  "Category": "ジャンル別,ライトノベル",
  "Points": 7
 },
 {
  "Asin": "B01IR01U58",
  "URL": "https://www.amazon.co.jp/dp/B01IR01U58?tag=99hatena-22&linkCode=ogi&th=1&psc=1",
  "ImageURL": "https://m.media-amazon.com/images/I/51qFzgTFk9L.jpg",
  "Publisher": "竹書房",
  "Contributor": "青砥あか(著)",
  "Booktype": "Kindle版",
  "Title": "結婚が破談になったら、課長と子作りすることになりました！？ (蜜夢文庫)",
  "Price": 363,
  "Category": "ジャンル別,ライトノベル",
  "Points": 4
 },
 {
  "Asin": "B07VC76SWJ",
  "URL": "https://www.amazon.co.jp/dp/B07VC76SWJ?tag=99hatena-22&linkCode=ogi&th=1&psc=1",
  "ImageURL": "https://m.media-amazon.com/images/I/51yHx5eubvL.jpg",
  "Publisher": "竹書房",
  "Contributor": "七福さゆり(著)",
  "Booktype": "Kindle版",
  "Title": "婚約破棄されたら異国の王子に溺愛されました 甘～いキスは悦楽の予感 (蜜猫文庫)",
  "Price": 418,
  "Category": "ジャンル別,ライトノベル",
  "Points": 4
 },
 {
  "Asin": "B07VC5T55G",
  "URL": "https://www.amazon.co.jp/dp/B07VC5T55G?tag=99hatena-22&linkCode=ogi&th=1&psc=1",
  "ImageURL": "https://m.media-amazon.com/images/I/61886ZumtHL.jpg",
  "Publisher": "竹書房",
  "Contributor": "すずね凜(著)",
  "Booktype": "Kindle版",
  "Title": "男装姫と絶倫王の激しすぎる蜜夜 (蜜猫文庫)",
  "Price": 413,
  "Category": "ジャンル別,ライトノベル",
  "Points": 4
 },
 {
  "Asin": "B071YYVC3F",
  "URL": "https://www.amazon.co.jp/dp/B071YYVC3F?tag=99hatena-22&linkCode=ogi&th=1&psc=1",
  "ImageURL": "https://m.media-amazon.com/images/I/61jkzNNebHL.jpg",
  "Publisher": "竹書房",
  "Contributor": "如月(著)",
  "Booktype": "Kindle版",
  "Title": "元帥公爵の新妻は愛されすぎて困り気味です (蜜猫文庫)",
  "Price": 385,
  "Category": "ジャンル別,ライトノベル",
  "Points": 4
 },
 {
  "Asin": "B07T288ZS6",
  "URL": "https://www.amazon.co.jp/dp/B07T288ZS6?tag=99hatena-22&linkCode=ogi&th=1&psc=1",
  "ImageURL": "https://m.media-amazon.com/images/I/51jczvPa1wL.jpg",
  "Publisher": "竹書房",
  "Contributor": "白石まと(著)",
  "Booktype": "Kindle版",
  "Title": "年下王子は最凶魔術師 世界征服より溺愛花嫁と甘い蜜月ですか (蜜猫ｎｏｖｅｌｓ)",
  "Price": 715,
  "Category": "ジャンル別,ライトノベル",
  "Points": 7
 },
 {
  "Asin": "B07VB31CPP",
  "URL": "https://www.amazon.co.jp/dp/B07VB31CPP?tag=99hatena-22&linkCode=ogi&th=1&psc=1",
  "ImageURL": "https://m.media-amazon.com/images/I/51uy99wsZyL.jpg",
  "Publisher": "竹書房",
  "Contributor": "月乃ひかり(著)",
  "Booktype": "Kindle版",
  "Title": "軍神王の秘巫女 【超】絶倫な王の夜伽は激しすぎます！ (ムーンドロップス)",
  "Price": 438,
  "Category": "ジャンル別,ライトノベル",
  "Points": 4
 },
 {
  "Asin": "B019C8S2YG",
  "URL": "https://www.amazon.co.jp/dp/B019C8S2YG?tag=99hatena-22&linkCode=ogi&th=1&psc=1",
  "ImageURL": "https://m.media-amazon.com/images/I/61dhuntGLxL.jpg",
  "Publisher": "竹書房",
  "Contributor": "青砥あか(著)",
  "Booktype": "Kindle版",
  "Title": "極道と夜の乙女 初めては淫らな契り (蜜夢文庫)",
  "Price": 363,
  "Category": "ジャンル別,ライトノベル",
  "Points": 4
 },
 {
  "Asin": "B07H9SR9TC",
  "URL": "https://www.amazon.co.jp/dp/B07H9SR9TC?tag=99hatena-22&linkCode=ogi&th=1&psc=1",
  "ImageURL": "https://m.media-amazon.com/images/I/51+79kiDYYL.jpg",
  "Publisher": "竹書房",
  "Contributor": "小出みき(著)",
  "Booktype": "Kindle版",
  "Title": "冷血公爵の溺愛花嫁　姫君は愛に惑う (蜜猫文庫)",
  "Price": 399,
  "Category": "ジャンル別,ライトノベル",
  "Points": 4
 },
 {
  "Asin": "B07YZ7ZJTZ",
  "URL": "https://www.amazon.co.jp/dp/B07YZ7ZJTZ?tag=99hatena-22&linkCode=ogi&th=1&psc=1",
  "ImageURL": "https://m.media-amazon.com/images/I/51R0D1P5I3L.jpg",
  "Publisher": "竹書房",
  "Contributor": "兎山もなか(著)",
  "Booktype": "Kindle版",
  "Title": "才川夫妻の恋愛事情 ９年目の愛妻家と赤ちゃん (蜜夢文庫)",
  "Price": 413,
  "Category": "ジャンル別,ライトノベル",
  "Points": 4
 },
 {
  "Asin": "B072Z8KH95",
  "URL": "https://www.amazon.co.jp/dp/B072Z8KH95?tag=99hatena-22&linkCode=ogi&th=1&psc=1",
  "ImageURL": "https://m.media-amazon.com/images/I/61o29Tw+cyL.jpg",
  "Publisher": "竹書房",
  "Contributor": "上主沙夜(著)",
  "Booktype": "Kindle版",
  "Title": "黒竜騎士の悩ましき熱愛 (蜜猫文庫)",
  "Price": 384,
  "Category": "ジャンル別,ライトノベル",
  "Points": 4
 },
 {
  "Asin": "B07MJQDWYZ",
  "URL": "https://www.amazon.co.jp/dp/B07MJQDWYZ?tag=99hatena-22&linkCode=ogi&th=1&psc=1",
  "ImageURL": "https://m.media-amazon.com/images/I/51FkcL0D2HL.jpg",
  "Publisher": "竹書房",
  "Contributor": "如月(著)",
  "Booktype": "Kindle版",
  "Title": "年上公爵と素直になれない若奥様 政略結婚は蜜夜の始まり (蜜猫文庫)",
  "Price": 408,
  "Category": "ジャンル別,ライトノベル",
  "Points": 4
 },
 {
  "Asin": "B01N537CKY",
  "URL": "https://www.amazon.co.jp/dp/B01N537CKY?tag=99hatena-22&linkCode=ogi&th=1&psc=1",
  "ImageURL": "https://m.media-amazon.com/images/I/51+5aJq6GTL.jpg",
  "Publisher": "竹書房",
  "Contributor": "兎山もなか(著)",
  "Booktype": "Kindle版",
  "Title": "イケメン兄弟から迫られていますがなんら問題ありません。 (蜜夢文庫)",
  "Price": 374,
  "Category": "ジャンル別,ライトノベル",
  "Points": 4
 },
 {
  "Asin": "B084STQ6FN",
  "URL": "https://www.amazon.co.jp/dp/B084STQ6FN?tag=99hatena-22&linkCode=ogi&th=1&psc=1",
  "ImageURL": "https://m.media-amazon.com/images/I/51J6o4edSyL.jpg",
  "Publisher": "竹書房",
  "Contributor": "葉月クロル(著)",
  "Booktype": "Kindle版",
  "Title": "成約率100％の婚活アドバイザーに“すべて”教えられてしまいました (蜜夢文庫)",
  "Price": 440,
  "Category": "ジャンル別,ライトノベル",
  "Points": 4
 },
 {
  "Asin": "B084SWKS52",
  "URL": "https://www.amazon.co.jp/dp/B084SWKS52?tag=99hatena-22&linkCode=ogi&th=1&psc=1",
  "ImageURL": "https://m.media-amazon.com/images/I/51LkdgR66jL.jpg",
  "Publisher": "竹書房",
  "Contributor": "小桜けい(著)",
  "Booktype": "Kindle版",
  "Title": "契約結婚だと思ったのに、なぜか王弟殿下に溺愛されています！？ 竜騎士サマと巣ごもり蜜月 (蜜猫ｎｏｖｅｌｓ)",
  "Price": 763,
  "Category": "ジャンル別,ライトノベル",
  "Points": 8
 },
 {
  "Asin": "B081F4D1YB",
  "URL": "https://www.amazon.co.jp/dp/B081F4D1YB?tag=99hatena-22&linkCode=ogi&th=1&psc=1",
  "ImageURL": "https://m.media-amazon.com/images/I/51Dl396YrCL.jpg",
  "Publisher": "竹書房",
  "Contributor": "ちろりん(著)",
  "Booktype": "Kindle版",
  "Title": "有能な軍人皇弟はカタブツ令嬢を甘く溺愛する (蜜猫文庫)",
  "Price": 440,
  "Category": "ジャンル別,ライトノベル",
  "Points": 4
 },
 {
  "Asin": "B06VWYVKPQ",
  "URL": "https://www.amazon.co.jp/dp/B06VWYVKPQ?tag=99hatena-22&linkCode=ogi&th=1&psc=1",
  "ImageURL": "https://m.media-amazon.com/images/I/617YPmca6kL.jpg",
  "Publisher": "竹書房",
  "Contributor": "すずね凜(著)",
  "Booktype": "Kindle版",
  "Title": "身代わりの新妻は伯爵の手で甘く囀る (蜜猫文庫)",
  "Price": 384,
  "Category": "ジャンル別,ライトノベル",
  "Points": 4
 },
 {
  "Asin": "B072Z62MN1",
  "URL": "https://www.amazon.co.jp/dp/B072Z62MN1?tag=99hatena-22&linkCode=ogi&th=1&psc=1",
  "ImageURL": "https://m.media-amazon.com/images/I/61hB2VUJrmL.jpg",
  "Publisher": "竹書房",
  "Contributor": "七福さゆり(著)",
  "Booktype": "Kindle版",
  "Title": "偏屈王と最愛の新妻 (蜜猫文庫)",
  "Price": 382,
  "Category": "ジャンル別,ライトノベル",
  "Points": 4
 },
 {
  "Asin": "B08732VX4C",
  "URL": "https://www.amazon.co.jp/dp/B08732VX4C?tag=99hatena-22&linkCode=ogi&th=1&psc=1",
  "ImageURL": "https://m.media-amazon.com/images/I/51xwBVVBgzL.jpg",
  "Publisher": "竹書房",
  "Contributor": "涼暮つき(著)",
  "Booktype": "Kindle版",
  "Title": "甘い誤算　特異体質の御曹司は運命のつがいを本能で愛す (蜜夢文庫)",
  "Price": 408,
  "Category": "ジャンル別,ライトノベル",
  "Points": 4
 },
 {
  "Asin": "B00PQDJM46",
  "URL": "https://www.amazon.co.jp/dp/B00PQDJM46?tag=99hatena-22&linkCode=ogi&th=1&psc=1",
  "ImageURL": "https://m.media-amazon.com/images/I/61BZUVwcLtL.jpg",
  "Publisher": "竹書房",
  "Contributor": "如月(著)",
  "Booktype": "Kindle版",
  "Title": "生贄の花嫁　背徳の罠と囚われの乙女 (蜜猫文庫)",
  "Price": 352,
  "Category": "ジャンル別,ライトノベル",
  "Points": 4
 },
 {
  "Asin": "B0797T7D9G",
  "URL": "https://www.amazon.co.jp/dp/B0797T7D9G?tag=99hatena-22&linkCode=ogi&th=1&psc=1",
  "ImageURL": "https://m.media-amazon.com/images/I/61tW9OkarqL.jpg",
  "Publisher": "竹書房",
  "Contributor": "御堂志生(著)",
  "Booktype": "Kindle版",
  "Title": "逃亡花嫁は海軍士官の王子様につかまえられました (蜜猫文庫)",
  "Price": 402,
  "Category": "ジャンル別,ライトノベル",
  "Points": 4
 },
 {
  "Asin": "B073ZWL4XV",
  "URL": "https://www.amazon.co.jp/dp/B073ZWL4XV?tag=99hatena-22&linkCode=ogi&th=1&psc=1",
  "ImageURL": "https://m.media-amazon.com/images/I/51i2T06G04L.jpg",
  "Publisher": "竹書房",
  "Contributor": "葉月クロル(著)",
  "Booktype": "Kindle版",
  "Title": "拾った地味メガネ男子はハイスペック王子！ いきなり結婚ってマジですか？ (蜜夢文庫)",
  "Price": 468,
  "Category": "ジャンル別,ライトノベル",
  "Points": 5
 },
 {
  "Asin": "B01D34LD00",
  "URL": "https://www.amazon.co.jp/dp/B01D34LD00?tag=99hatena-22&linkCode=ogi&th=1&psc=1",
  "ImageURL": "https://m.media-amazon.com/images/I/51LTcN6DFnL.jpg",
  "Publisher": "竹書房",
  "Contributor": "兎山もなか(著)",
  "Booktype": "Kindle版",
  "Title": "編集さん（←元カノ）に謀られまして 禁欲作家の恋と欲望 (蜜夢文庫)",
  "Price": 363,
  "Category": "ジャンル別,ライトノベル",
  "Points": 4
 },
 {
  "Asin": "B077GS3PB7",
  "URL": "https://www.amazon.co.jp/dp/B077GS3PB7?tag=99hatena-22&linkCode=ogi&th=1&psc=1",
  "ImageURL": "https://m.media-amazon.com/images/I/51OlAlvt7jL.jpg",
  "Publisher": "竹書房",
  "Contributor": "兎山もなか(著)",
  "Booktype": "Kindle版",
  "Title": "才川夫妻の恋愛事情　7年じっくり調教されました (蜜夢文庫)",
  "Price": 413,
  "Category": "ジャンル別,ライトノベル",
  "Points": 4
 },
 {
  "Asin": "B08732321V",
  "URL": "https://www.amazon.co.jp/dp/B08732321V?tag=99hatena-22&linkCode=ogi&th=1&psc=1",
  "ImageURL": "https://m.media-amazon.com/images/I/51wW1C-l1cL.jpg",
  "Publisher": "竹書房",
  "Contributor": "藍井恵(著)",
  "Booktype": "Kindle版",
  "Title": "異世界で推しの溺愛が止まりません！　転移したらめっちゃ愛されヒロインでした♡ (蜜猫ｎｏｖｅｌｓ)",
  "Price": 770,
  "Category": "ジャンル別,ライトノベル",
  "Points": 8
 },
 {
  "Asin": "B07D4CGDL8",
  "URL": "https://www.amazon.co.jp/dp/B07D4CGDL8?tag=99hatena-22&linkCode=ogi&th=1&psc=1",
  "ImageURL": "https://m.media-amazon.com/images/I/616M0bu8AAL.jpg",
  "Publisher": "竹書房",
  "Contributor": "兎山もなか(著)",
  "Booktype": "Kindle版",
  "Title": "黙って私を抱きなさい！～年上眼鏡秘書は純情女社長を大事にしすぎている (蜜夢文庫)",
  "Price": 440,
  "Category": "ジャンル別,ライトノベル",
  "Points": 4
 },
 {
  "Asin": "B07FFQSHMM",
  "URL": "https://www.amazon.co.jp/dp/B07FFQSHMM?tag=99hatena-22&linkCode=ogi&th=1&psc=1",
  "ImageURL": "https://m.media-amazon.com/images/I/51IF-eORXgL.jpg",
  "Publisher": "竹書房",
  "Contributor": "伽月るーこ(著)",
  "Booktype": "Kindle版",
  "Title": "国王陛下は身代わりの花嫁を熱愛中 (蜜猫文庫)",
  "Price": 397,
  "Category": "ジャンル別,ライトノベル",
  "Points": 4
 },
 {
  "Asin": "B07XVDJMK4",
  "URL": "https://www.amazon.co.jp/dp/B07XVDJMK4?tag=99hatena-22&linkCode=ogi&th=1&psc=1",
  "ImageURL": "https://m.media-amazon.com/images/I/51Myu80Nh7L.jpg",
  "Publisher": "竹書房",
  "Contributor": "麻生みかり(著)",
  "Booktype": "Kindle版",
  "Title": "ご主人さまはご機嫌ななめ イケメン侯爵と逃亡花嫁の甘ふわ蜜愛♡ (蜜猫文庫)",
  "Price": 440,
  "Category": "ジャンル別,ライトノベル",
  "Points": 4
 },
 {
  "Asin": "B0797RFYZ5",
  "URL": "https://www.amazon.co.jp/dp/B0797RFYZ5?tag=99hatena-22&linkCode=ogi&th=1&psc=1",
  "ImageURL": "https://m.media-amazon.com/images/I/51O0YVZwPML.jpg",
  "Publisher": "竹書房",
  "Contributor": "小出みき(著)",
  "Booktype": "Kindle版",
  "Title": "鋼の元帥と見捨てられた王女 銀の花嫁は蜜夜に溺れる (蜜猫文庫)",
  "Price": 402,
  "Category": "ジャンル別,ライトノベル",
  "Points": 4
 },
 {
  "Asin": "B00TX5DM8A",
  "URL": "https://www.amazon.co.jp/dp/B00TX5DM8A?tag=99hatena-22&linkCode=ogi&th=1&psc=1",
  "ImageURL": "https://m.media-amazon.com/images/I/61TC0GbKHmL.jpg",
  "Publisher": "竹書房",
  "Contributor": "森本あき(著)",
  "Booktype": "Kindle版",
  "Title": "新妻はみだらに濡れる (蜜猫文庫)",
  "Price": 352,
  "Category": "ジャンル別,ライトノベル",
  "Points": 4
 },
 {
  "Asin": "B00V31CE2M",
  "URL": "https://www.amazon.co.jp/dp/B00V31CE2M?tag=99hatena-22&linkCode=ogi&th=1&psc=1",
  "ImageURL": "https://m.media-amazon.com/images/I/61vAEjb2r6L.jpg",
  "Publisher": "竹書房",
  "Contributor": "白石まと(著)",
  "Booktype": "Kindle版",
  "Title": "ミッシング　王太子妃の密室の淫戯 (蜜猫文庫)",
  "Price": 352,
  "Category": "ジャンル別,ライトノベル",
  "Points": 4
 },
 {
  "Asin": "B07DVF48DC",
  "URL": "https://www.amazon.co.jp/dp/B07DVF48DC?tag=99hatena-22&linkCode=ogi&th=1&psc=1",
  "ImageURL": "https://m.media-amazon.com/images/I/61bBRCknXpL.jpg",
  "Publisher": "竹書房",
  "Contributor": "麻生ミカリ(著)",
  "Booktype": "Kindle版",
  "Title": "憧れの聖騎士さまと結婚したらイジワルされつつ溺愛されてます (蜜猫文庫)",
  "Price": 402,
  "Category": "ジャンル別,ライトノベル",
  "Points": 4
 },
 {
  "Asin": "B078WMDRRD",
  "URL": "https://www.amazon.co.jp/dp/B078WMDRRD?tag=99hatena-22&linkCode=ogi&th=1&psc=1",
  "ImageURL": "https://m.media-amazon.com/images/I/611aNRftVdL.jpg",
  "Publisher": "竹書房",
  "Contributor": "椋本梨戸(著)",
  "Booktype": "Kindle版",
  "Title": "怖がりの新妻は竜王に、永く優しく愛されました。 (ムーンドロップス)",
  "Price": 660,
  "Category": "ジャンル別,ライトノベル",
  "Points": 7
 },
 {
  "Asin": "B07RQRM6WG",
  "URL": "https://www.amazon.co.jp/dp/B07RQRM6WG?tag=99hatena-22&linkCode=ogi&th=1&psc=1",
  "ImageURL": "https://m.media-amazon.com/images/I/51dz6V-CnoL.jpg",
  "Publisher": "竹書房",
  "Contributor": "藍杜雫(著)",
  "Booktype": "Kindle版",
  "Title": "麗しの公爵の蜜愛の箱庭　友達だった彼が夫になったあとで (蜜猫文庫)",
  "Price": 413,
  "Category": "ジャンル別,ライトノベル",
  "Points": 4
 },
 {
  "Asin": "B07JC9RHLR",
  "URL": "https://www.amazon.co.jp/dp/B07JC9RHLR?tag=99hatena-22&linkCode=ogi&th=1&psc=1",
  "ImageURL": "https://m.media-amazon.com/images/I/51cuilcZkWL.jpg",
  "Publisher": "竹書房",
  "Contributor": "兎山もなか(著)",
  "Booktype": "Kindle版",
  "Title": "才川夫妻の恋愛事情 8年目の溺愛と子作り宣言 (蜜夢文庫)",
  "Price": 413,
  "Category": "ジャンル別,ライトノベル",
  "Points": 4
 },
 {
  "Asin": "B078WMX5BP",
  "URL": "https://www.amazon.co.jp/dp/B078WMX5BP?tag=99hatena-22&linkCode=ogi&th=1&psc=1",
  "ImageURL": "https://m.media-amazon.com/images/I/61l9lc4arOL.jpg",
  "Publisher": "竹書房",
  "Contributor": "葛餅(著)",
  "Booktype": "Kindle版",
  "Title": "数学女子が転生したら、次期公爵に愛され過ぎてピンチです！ (ムーンドロップス)",
  "Price": 660,
  "Category": "ジャンル別,ライトノベル",
  "Points": 7
 },
 {
  "Asin": "B06W9LTNMW",
  "URL": "https://www.amazon.co.jp/dp/B06W9LTNMW?tag=99hatena-22&linkCode=ogi&th=1&psc=1",
  "ImageURL": "https://m.media-amazon.com/images/I/61cGBKtV+VL.jpg",
  "Publisher": "竹書房",
  "Contributor": "七福さゆり(著)",
  "Booktype": "Kindle版",
  "Title": "公爵様の可愛い恋人 (蜜猫文庫)",
  "Price": 382,
  "Category": "ジャンル別,ライトノベル",
  "Points": 4
 },
 {
  "Asin": "B07QM3C21Q",
  "URL": "https://www.amazon.co.jp/dp/B07QM3C21Q?tag=99hatena-22&linkCode=ogi&th=1&psc=1",
  "ImageURL": "https://m.media-amazon.com/images/I/51UMnaChsRL.jpg",
  "Publisher": "竹書房",
  "Contributor": "兎山もなか(著)",
  "Booktype": "Kindle版",
  "Title": "君が何度も××するから　ふしだらなスーツと眼鏡、時々エッチな夢 (蜜夢文庫)",
  "Price": 440,
  "Category": "ジャンル別,ライトノベル",
  "Points": 4
 },
 {
  "Asin": "B081DQR4P8",
  "URL": "https://www.amazon.co.jp/dp/B081DQR4P8?tag=99hatena-22&linkCode=ogi&th=1&psc=1",
  "ImageURL": "https://m.media-amazon.com/images/I/51Njpmd9hlL.jpg",
  "Publisher": "竹書房",
  "Contributor": "日車メレ(著)",
  "Booktype": "Kindle版",
  "Title": "墓守公爵と契約花嫁　ご先祖様、寝室は立ち入り厳禁です！ (ムーンドロップス)",
  "Price": 440,
  "Category": "ジャンル別,ライトノベル",
  "Points": 4
 },
 {
  "Asin": "B01D34LD0U",
  "URL": "https://www.amazon.co.jp/dp/B01D34LD0U?tag=99hatena-22&linkCode=ogi&th=1&psc=1",
  "ImageURL": "https://m.media-amazon.com/images/I/612c6w2gmyL.jpg",
  "Publisher": "竹書房",
  "Contributor": "すずね凜(著)",
  "Booktype": "Kindle版",
  "Title": "溺愛偽婚 新妻は淫らに乱され (蜜猫文庫)",
  "Price": 352,
  "Category": "ジャンル別,ライトノベル",
  "Points": 4
 },
 {
  "Asin": "B07GF7Z29R",
  "URL": "https://www.amazon.co.jp/dp/B07GF7Z29R?tag=99hatena-22&linkCode=ogi&th=1&psc=1",
  "ImageURL": "https://m.media-amazon.com/images/I/51TEtXMg2eL.jpg",
  "Publisher": "竹書房",
  "Contributor": "奏多(著)",
  "Booktype": "Kindle版",
  "Title": "隣人の声に欲情する彼女は、拗らせ上司の誘惑にも逆らえません (蜜夢文庫)",
  "Price": 440,
  "Category": "ジャンル別,ライトノベル",
  "Points": 4
 },
 {
  "Asin": "B07YZ5Q2QG",
  "URL": "https://www.amazon.co.jp/dp/B07YZ5Q2QG?tag=99hatena-22&linkCode=ogi&th=1&psc=1",
  "ImageURL": "https://m.media-amazon.com/images/I/51iFc-xJgDL.jpg",
  "Publisher": "竹書房",
  "Contributor": "奏多(著)",
  "Booktype": "Kindle版",
  "Title": "硝煙は溺愛の香り　黒き獣は偽花嫁を淫らに堕とす (蜜夢文庫)",
  "Price": 440,
  "Category": "ジャンル別,ライトノベル",
  "Points": 4
 },
 {
  "Asin": "B01D34LCXS",
  "URL": "https://www.amazon.co.jp/dp/B01D34LCXS?tag=99hatena-22&linkCode=ogi&th=1&psc=1",
  "ImageURL": "https://m.media-amazon.com/images/I/61ByCzCOGSL.jpg",
  "Publisher": "竹書房",
  "Contributor": "みかづき紅月(著)",
  "Booktype": "Kindle版",
  "Title": "愛執のレッスン オペラ座の闇に抱かれて (蜜猫文庫)",
  "Price": 352,
  "Category": "ジャンル別,ライトノベル",
  "Points": 4
 },
 {
  "Asin": "B077GSV9Y8",
  "URL": "https://www.amazon.co.jp/dp/B077GSV9Y8?tag=99hatena-22&linkCode=ogi&th=1&psc=1",
  "ImageURL": "https://m.media-amazon.com/images/I/51gX0XzEmrL.jpg",
  "Publisher": "竹書房",
  "Contributor": "かのこ(著)",
  "Booktype": "Kindle版",
  "Title": "アブノーマル・スイッチ～草食系同期のSな本性～ (蜜夢文庫)",
  "Price": 413,
  "Category": "ジャンル別,ライトノベル",
  "Points": 4
 },
 {
  "Asin": "B07PQHNQBP",
  "URL": "https://www.amazon.co.jp/dp/B07PQHNQBP?tag=99hatena-22&linkCode=ogi&th=1&psc=1",
  "ImageURL": "https://m.media-amazon.com/images/I/51ImNOjDxrL.jpg",
  "Publisher": "竹書房",
  "Contributor": "青砥あか(著)",
  "Booktype": "Kindle版",
  "Title": "愛玩調教 過保護すぎる飼い主の淫靡な企み (ムーンドロップス)",
  "Price": 440,
  "Category": "ジャンル別,ライトノベル",
  "Points": 4
 },
 {
  "Asin": "B07NPM2BTR",
  "URL": "https://www.amazon.co.jp/dp/B07NPM2BTR?tag=99hatena-22&linkCode=ogi&th=1&psc=1",
  "ImageURL": "https://m.media-amazon.com/images/I/51-bvmjwDIL.jpg",
  "Publisher": "竹書房",
  "Contributor": "かのこ(著)",
  "Booktype": "Kindle版",
  "Title": "侵蝕する愛　通勤電車の秘蜜 (蜜夢文庫)",
  "Price": 413,
  "Category": "ジャンル別,ライトノベル",
  "Points": 4
 },
 {
  "Asin": "B081DQNM7H",
  "URL": "https://www.amazon.co.jp/dp/B081DQNM7H?tag=99hatena-22&linkCode=ogi&th=1&psc=1",
  "ImageURL": "https://m.media-amazon.com/images/I/51iftJ46qYL.jpg",
  "Publisher": "竹書房",
  "Contributor": "すずね凜(著)",
  "Booktype": "Kindle版",
  "Title": "絶対君主の甘美な寵愛　薄命の王女は愛に乱れ堕ちて (蜜猫文庫)",
  "Price": 440,
  "Category": "ジャンル別,ライトノベル",
  "Points": 4
 },
 {
  "Asin": "B082PSF5ZS",
  "URL": "https://www.amazon.co.jp/dp/B082PSF5ZS?tag=99hatena-22&linkCode=ogi&th=1&psc=1",
  "ImageURL": "https://m.media-amazon.com/images/I/51-VOs9-9FL.jpg",
  "Publisher": "竹書房",
  "Contributor": "玉紀直(著)",
  "Booktype": "Kindle版",
  "Title": "年下恋愛対象外！チャラい後輩君は真面目一途な絶倫でした (蜜夢文庫)",
  "Price": 440,
  "Category": "ジャンル別,ライトノベル",
  "Points": 4
 },
 {
  "Asin": "B07YZ83FDT",
  "URL": "https://www.amazon.co.jp/dp/B07YZ83FDT?tag=99hatena-22&linkCode=ogi&th=1&psc=1",
  "ImageURL": "https://m.media-amazon.com/images/I/5192F7DzzsL.jpg",
  "Publisher": "竹書房",
  "Contributor": "水嶋凛(著)",
  "Booktype": "Kindle版",
  "Title": "乙女ゲームのモブに転生したので全力で推しを応援します！ 蕩けるキスは誰のもの？ (蜜猫ｎｏｖｅｌｓ)",
  "Price": 770,
  "Category": "ジャンル別,ライトノベル",
  "Points": 8
 },
 {
  "Asin": "B07KG33FKF",
  "URL": "https://www.amazon.co.jp/dp/B07KG33FKF?tag=99hatena-22&linkCode=ogi&th=1&psc=1",
  "ImageURL": "https://m.media-amazon.com/images/I/516BMJjDN2L.jpg",
  "Publisher": "竹書房",
  "Contributor": "七福さゆり(著)",
  "Booktype": "Kindle版",
  "Title": "カタブツ騎士団長と恋する令嬢 (蜜猫文庫)",
  "Price": 402,
  "Category": "ジャンル別,ライトノベル",
  "Points": 4
 },
 {
  "Asin": "B077F673ZK",
  "URL": "https://www.amazon.co.jp/dp/B077F673ZK?tag=99hatena-22&linkCode=ogi&th=1&psc=1",
  "ImageURL": "https://m.media-amazon.com/images/I/61yFe-bCLfL.jpg",
  "Publisher": "竹書房",
  "Contributor": "天草白(著)",
  "Booktype": "Kindle版",
  "Title": "エルフの魔法剣士に転生した俺の無双ハーレムルート　１ (ヴァリアントノベルズ)",
  "Price": 605,
  "Category": "ジャンル別,ライトノベル",
  "Points": 6
 },
 {
  "Asin": "B00ZTXKHWE",
  "URL": "https://www.amazon.co.jp/dp/B00ZTXKHWE?tag=99hatena-22&linkCode=ogi&th=1&psc=1",
  "ImageURL": "https://m.media-amazon.com/images/I/61XrujZu7HL.jpg",
  "Publisher": "竹書房",
  "Contributor": "みかづき紅月(著)",
  "Booktype": "Kindle版",
  "Title": "絶対君主の独占愛 仮面に隠された蜜戯 (蜜猫文庫)",
  "Price": 352,
  "Category": "ジャンル別,ライトノベル",
  "Points": 4
 },
 {
  "Asin": "B00ZTXKHDI",
  "URL": "https://www.amazon.co.jp/dp/B00ZTXKHDI?tag=99hatena-22&linkCode=ogi&th=1&psc=1",
  "ImageURL": "https://m.media-amazon.com/images/I/61+1+XLNu+L.jpg",
  "Publisher": "竹書房",
  "Contributor": "すずね凜(著)",
  "Booktype": "Kindle版",
  "Title": "皇帝陛下の溺愛婚 獅子は子猫を甘やかす (蜜猫文庫)",
  "Price": 352,
  "Category": "ジャンル別,ライトノベル",
  "Points": 4
 },
 {
  "Asin": "B00ZTXKHA6",
  "URL": "https://www.amazon.co.jp/dp/B00ZTXKHA6?tag=99hatena-22&linkCode=ogi&th=1&psc=1",
  "ImageURL": "https://m.media-amazon.com/images/I/61Xzm7SS9SL.jpg",
  "Publisher": "竹書房",
  "Contributor": "如月(著)",
  "Booktype": "Kindle版",
  "Title": "蜜夜 薔薇の花嫁は愛に溺れる (蜜猫文庫)",
  "Price": 352,
  "Category": "ジャンル別,ライトノベル",
  "Points": 4
 },
 {
  "Asin": "B07CGB4B5J",
  "URL": "https://www.amazon.co.jp/dp/B07CGB4B5J?tag=99hatena-22&linkCode=ogi&th=1&psc=1",
  "ImageURL": "https://m.media-amazon.com/images/I/61Qth3nV+EL.jpg",
  "Publisher": "竹書房",
  "Contributor": "天草白(著)",
  "Booktype": "Kindle版",
  "Title": "エルフの魔法剣士に転生した俺の無双ハーレムルート　２ (ヴァリアントノベルズ)",
  "Price": 605,
  "Category": "ジャンル別,ライトノベル",
  "Points": 6
 },
 {
  "Asin": "B073ZVJ9FG",
  "URL": "https://www.amazon.co.jp/dp/B073ZVJ9FG?tag=99hatena-22&linkCode=ogi&th=1&psc=1",
  "ImageURL": "https://m.media-amazon.com/images/I/61faaIjVQmL.jpg",
  "Publisher": "竹書房",
  "Contributor": "青砥あか(著)",
  "Booktype": "Kindle版",
  "Title": "入れ替わったら、オレ様彼氏とエッチする運命でした！ (蜜夢文庫)",
  "Price": 413,
  "Category": "ジャンル別,ライトノベル",
  "Points": 4
 },
 {
  "Asin": "B07PQJ7RNL",
  "URL": "https://www.amazon.co.jp/dp/B07PQJ7RNL?tag=99hatena-22&linkCode=ogi&th=1&psc=1",
  "ImageURL": "https://m.media-amazon.com/images/I/51kKVVt9LVL.jpg",
  "Publisher": "竹書房",
  "Contributor": "上主沙夜(著)",
  "Booktype": "Kindle版",
  "Title": "帝國の華嫁　英雄皇帝は政略結婚の姫君を溺愛する (蜜猫文庫)",
  "Price": 440,
  "Category": "ジャンル別,ライトノベル",
  "Points": 4
 },
 {
  "Asin": "B074M4HY7G",
  "URL": "https://www.amazon.co.jp/dp/B074M4HY7G?tag=99hatena-22&linkCode=ogi&th=1&psc=1",
  "ImageURL": "https://m.media-amazon.com/images/I/61A9TCGO4FL.jpg",
  "Publisher": "竹書房",
  "Contributor": "兎山もなか(著)",
  "Booktype": "Kindle版",
  "Title": "異世界で愛され姫になったら現実が変わりはじめました。 (ムーンドロップス)",
  "Price": 660,
  "Category": "ジャンル別,ライトノベル",
  "Points": 7
 },
 {
  "Asin": "B07GF6LZSJ",
  "URL": "https://www.amazon.co.jp/dp/B07GF6LZSJ?tag=99hatena-22&linkCode=ogi&th=1&psc=1",
  "ImageURL": "https://m.media-amazon.com/images/I/51cFjWaODgL.jpg",
  "Publisher": "竹書房",
  "Contributor": "ほーち(著)",
  "Booktype": "Kindle版",
  "Title": "聖騎士に生まれ変わった俺は異世界再生のため子作りに励む　２ (ヴァリアントノベルズ)",
  "Price": 605,
  "Category": "ジャンル別,ライトノベル",
  "Points": 6
 },
 {
  "Asin": "B07CH3KQJQ",
  "URL": "https://www.amazon.co.jp/dp/B07CH3KQJQ?tag=99hatena-22&linkCode=ogi&th=1&psc=1",
  "ImageURL": "https://m.media-amazon.com/images/I/612h3OJx3EL.jpg",
  "Publisher": "竹書房",
  "Contributor": "藍杜雫(著)",
  "Booktype": "Kindle版",
  "Title": "聖爵猊下とできちゃった婚！？ これが夫婦円満の秘訣です！ (蜜猫文庫)",
  "Price": 402,
  "Category": "ジャンル別,ライトノベル",
  "Points": 4
 },
 {
  "Asin": "B07RRVDS2M",
  "URL": "https://www.amazon.co.jp/dp/B07RRVDS2M?tag=99hatena-22&linkCode=ogi&th=1&psc=1",
  "ImageURL": "https://m.media-amazon.com/images/I/51Jp8Y2VilL.jpg",
  "Publisher": "竹書房",
  "Contributor": "藍井恵(著)",
  "Booktype": "Kindle版",
  "Title": "元帥公爵に熱望されて結婚したら、とろとろに蜜愛されたけれど何か裏がありそうです！？ (蜜猫文庫)",
  "Price": 413,
  "Category": "ジャンル別,ライトノベル",
  "Points": 4
 },
 {
  "Asin": "B079T1VQHW",
  "URL": "https://www.amazon.co.jp/dp/B079T1VQHW?tag=99hatena-22&linkCode=ogi&th=1&psc=1",
  "ImageURL": "https://m.media-amazon.com/images/I/61z3RO7oAEL.jpg",
  "Publisher": "竹書房",
  "Contributor": "ほーち(著)",
  "Booktype": "Kindle版",
  "Title": "聖騎士に生まれ変わった俺は異世界再生のため子作りに励む　１ (ヴァリアントノベルズ)",
  "Price": 605,
  "Category": "ジャンル別,ライトノベル",
  "Points": 6
 },
 {
  "Asin": "B074K23HSB",
  "URL": "https://www.amazon.co.jp/dp/B074K23HSB?tag=99hatena-22&linkCode=ogi&th=1&psc=1",
  "ImageURL": "https://m.media-amazon.com/images/I/51ZcXWY9F8L.jpg",
  "Publisher": "竹書房",
  "Contributor": "すずね凜(著)",
  "Booktype": "Kindle版",
  "Title": "スキャンダラスな王女は異国の王の溺愛に甘くとろけて (蜜猫ｎｏｖｅｌｓ)",
  "Price": 660,
  "Category": "ジャンル別,ライトノベル",
  "Points": 7
 },
 {
  "Asin": "B072BMHXFN",
  "URL": "https://www.amazon.co.jp/dp/B072BMHXFN?tag=99hatena-22&linkCode=ogi&th=1&psc=1",
  "ImageURL": "https://m.media-amazon.com/images/I/61z26sh8qlL.jpg",
  "Publisher": "竹書房",
  "Contributor": "秀香穂里(著)",
  "Booktype": "Kindle版",
  "Title": "王子殿下の可愛いお針子　秘め事は塔の上で (蜜猫文庫)",
  "Price": 385,
  "Category": "ジャンル別,ライトノベル",
  "Points": 4
 },
 {
  "Asin": "B085W315KX",
  "URL": "https://www.amazon.co.jp/dp/B085W315KX?tag=99hatena-22&linkCode=ogi&th=1&psc=1",
  "ImageURL": "https://m.media-amazon.com/images/I/5159msbBKIL.jpg",
  "Publisher": "竹書房",
  "Contributor": "当麻咲来(著)",
  "Booktype": "Kindle版",
  "Title": "王立魔法図書館の[錠前]は執愛の蜜獄に囚われて (ムーンドロップス)",
  "Price": 440,
  "Category": "ジャンル別,ライトノベル",
  "Points": 4
 },
 {
  "Asin": "B075R365JR",
  "URL": "https://www.amazon.co.jp/dp/B075R365JR?tag=99hatena-22&linkCode=ogi&th=1&psc=1",
  "ImageURL": "https://m.media-amazon.com/images/I/51GysK1Qd-L.jpg",
  "Publisher": "竹書房",
  "Contributor": "御堂志生(著)",
  "Booktype": "Kindle版",
  "Title": "エリート弁護士は不機嫌に溺愛する～解約不可の服従契約～ (蜜夢文庫)",
  "Price": 413,
  "Category": "ジャンル別,ライトノベル",
  "Points": 4
 },
 {
  "Asin": "B07WFNMNHL",
  "URL": "https://www.amazon.co.jp/dp/B07WFNMNHL?tag=99hatena-22&linkCode=ogi&th=1&psc=1",
  "ImageURL": "https://m.media-amazon.com/images/I/51IAa154g4L.jpg",
  "Publisher": "竹書房",
  "Contributor": "御堂志生(著)",
  "Booktype": "Kindle版",
  "Title": "欲望の視線　冷酷な御曹司は姫の純潔を瞳で奪う (蜜夢文庫)",
  "Price": 440,
  "Category": "ジャンル別,ライトノベル",
  "Points": 4
 },
 {
  "Asin": "B075QYX18C",
  "URL": "https://www.amazon.co.jp/dp/B075QYX18C?tag=99hatena-22&linkCode=ogi&th=1&psc=1",
  "ImageURL": "https://m.media-amazon.com/images/I/51LZ8emV5+L.jpg",
  "Publisher": "竹書房",
  "Contributor": "桃城猫緒(著)",
  "Booktype": "Kindle版",
  "Title": "処女ですが復讐のため上司に抱かれます！ (蜜夢文庫)",
  "Price": 385,
  "Category": "ジャンル別,ライトノベル",
  "Points": 4
 },
 {
  "Asin": "B00ZTXKI3W",
  "URL": "https://www.amazon.co.jp/dp/B00ZTXKI3W?tag=99hatena-22&linkCode=ogi&th=1&psc=1",
  "ImageURL": "https://m.media-amazon.com/images/I/61xCSsWhcgL.jpg",
  "Publisher": "竹書房",
  "Contributor": "藍杜雫(著)",
  "Booktype": "Kindle版",
  "Title": "戦神皇帝の初夜 姫は異教の宴に喘ぐ (蜜猫文庫)",
  "Price": 352,
  "Category": "ジャンル別,ライトノベル",
  "Points": 4
 },
 {
  "Asin": "B082PVYXQL",
  "URL": "https://www.amazon.co.jp/dp/B082PVYXQL?tag=99hatena-22&linkCode=ogi&th=1&psc=1",
  "ImageURL": "https://m.media-amazon.com/images/I/51+ysImGEAL.jpg",
  "Publisher": "竹書房",
  "Contributor": "上主沙夜(著)",
  "Booktype": "Kindle版",
  "Title": "平安あやかし恋絵巻　麗しの東宮さまと秘密の夜 (蜜猫ｎｏｖｅｌｓ)",
  "Price": 770,
  "Category": "ジャンル別,ライトノベル",
  "Points": 8
 },
 {
  "Asin": "B00TX5DMB2",
  "URL": "https://www.amazon.co.jp/dp/B00TX5DMB2?tag=99hatena-22&linkCode=ogi&th=1&psc=1",
  "ImageURL": "https://m.media-amazon.com/images/I/51HGgi370PL.jpg",
  "Publisher": "竹書房",
  "Contributor": "七福さゆり(著)",
  "Booktype": "Kindle版",
  "Title": "愛淫の代償　囚われの小鳥姫 (蜜猫文庫)",
  "Price": 352,
  "Category": "ジャンル別,ライトノベル",
  "Points": 4
 },
 {
  "Asin": "B01MR8W39J",
  "URL": "https://www.amazon.co.jp/dp/B01MR8W39J?tag=99hatena-22&linkCode=ogi&th=1&psc=1",
  "ImageURL": "https://m.media-amazon.com/images/I/61sEypKsDOL.jpg",
  "Publisher": "竹書房",
  "Contributor": "麻生ミカリ(著)",
  "Booktype": "Kindle版",
  "Title": "国王陛下の溺愛王妃 (蜜猫文庫)",
  "Price": 385,
  "Category": "ジャンル別,ライトノベル",
  "Points": 4
 },
 {
  "Asin": "B07RRTPGVF",
  "URL": "https://www.amazon.co.jp/dp/B07RRTPGVF?tag=99hatena-22&linkCode=ogi&th=1&psc=1",
  "ImageURL": "https://m.media-amazon.com/images/I/51KhBzv7TrL.jpg",
  "Publisher": "竹書房",
  "Contributor": "当麻咲来(著)",
  "Booktype": "Kindle版",
  "Title": "失神するほど愛されて　悪魔は聖姫を夜ごと悦楽に堕とす (ムーンドロップス)",
  "Price": 468,
  "Category": "ジャンル別,ライトノベル",
  "Points": 5
 },
 {
  "Asin": "B01LYVMTM3",
  "URL": "https://www.amazon.co.jp/dp/B01LYVMTM3?tag=99hatena-22&linkCode=ogi&th=1&psc=1",
  "ImageURL": "https://m.media-amazon.com/images/I/61FeBtZQt+L.jpg",
  "Publisher": "竹書房",
  "Contributor": "みかづき紅月(著)",
  "Booktype": "Kindle版",
  "Title": "奪愛トライアングル 悦楽と執着の蜜夜 (蜜猫文庫)",
  "Price": 352,
  "Category": "ジャンル別,ライトノベル",
  "Points": 4
 },
 {
  "Asin": "B07XLRRB42",
  "URL": "https://www.amazon.co.jp/dp/B07XLRRB42?tag=99hatena-22&linkCode=ogi&th=1&psc=1",
  "ImageURL": "https://m.media-amazon.com/images/I/514IPSZT0qL.jpg",
  "Publisher": "竹書房",
  "Contributor": "山野辺りり(著)",
  "Booktype": "Kindle版",
  "Title": "伯爵令息は箱入り令嬢を甘やかして溺愛したい　秘蜜の夜にとろけるキスを (蜜猫文庫)",
  "Price": 440,
  "Category": "ジャンル別,ライトノベル",
  "Points": 4
 },
 {
  "Asin": "B083WB2YBB",
  "URL": "https://www.amazon.co.jp/dp/B083WB2YBB?tag=99hatena-22&linkCode=ogi&th=1&psc=1",
  "ImageURL": "https://m.media-amazon.com/images/I/51zPRs1L-EL.jpg",
  "Publisher": "竹書房",
  "Contributor": "イシクロ(著)",
  "Booktype": "Kindle版",
  "Title": "偽りの吸血姫が本物になるまで　身代わり処女は甘い楔に啼く (ムーンドロップス)",
  "Price": 468,
  "Category": "ジャンル別,ライトノベル",
  "Points": 5
 },
 {
  "Asin": "B0725S45FR",
  "URL": "https://www.amazon.co.jp/dp/B0725S45FR?tag=99hatena-22&linkCode=ogi&th=1&psc=1",
  "ImageURL": "https://m.media-amazon.com/images/I/51Uhwu6tknL.jpg",
  "Publisher": "竹書房",
  "Contributor": "玉紀直(著)",
  "Booktype": "Kindle版",
  "Title": "聖人君子が豹変したら意外と肉食だった件 (蜜夢文庫)",
  "Price": 385,
  "Category": "ジャンル別,ライトノベル",
  "Points": 4
 },
 {
  "Asin": "B0792V455N",
  "URL": "https://www.amazon.co.jp/dp/B0792V455N?tag=99hatena-22&linkCode=ogi&th=1&psc=1",
  "ImageURL": "https://m.media-amazon.com/images/I/619BShRuB2L.jpg",
  "Publisher": "竹書房",
  "Contributor": "藍井恵(著)",
  "Booktype": "Kindle版",
  "Title": "運命の乙女を娶った王太子は新妻にご執心！ (蜜猫文庫)",
  "Price": 402,
  "Category": "ジャンル別,ライトノベル",
  "Points": 4
 },
 {
  "Asin": "B00VRE9RX4",
  "URL": "https://www.amazon.co.jp/dp/B00VRE9RX4?tag=99hatena-22&linkCode=ogi&th=1&psc=1",
  "ImageURL": "https://m.media-amazon.com/images/I/61Lnx8vi6WL.jpg",
  "Publisher": "竹書房",
  "Contributor": "斎王ことり(著)",
  "Booktype": "Kindle版",
  "Title": "ベル姫の華麗なる結婚　正しい初夜の奪い方 (蜜猫文庫)",
  "Price": 360,
  "Category": "ジャンル別,ライトノベル",
  "Points": 4
 },
 {
  "Asin": "B017R0TUX8",
  "URL": "https://www.amazon.co.jp/dp/B017R0TUX8?tag=99hatena-22&linkCode=ogi&th=1&psc=1",
  "ImageURL": "https://m.media-amazon.com/images/I/51vvSTy+6CL.jpg",
  "Publisher": "竹書房",
  "Contributor": "御堂志生(著)",
  "Booktype": "Kindle版",
  "Title": "覇王の花嫁 (蜜猫文庫)",
  "Price": 352,
  "Category": "ジャンル別,ライトノベル",
  "Points": 4
 },
 {
  "Asin": "B07T1921RY",
  "URL": "https://www.amazon.co.jp/dp/B07T1921RY?tag=99hatena-22&linkCode=ogi&th=1&psc=1",
  "ImageURL": "https://m.media-amazon.com/images/I/51Br2PkNC8L.jpg",
  "Publisher": "竹書房",
  "Contributor": "東国不動(著)",
  "Booktype": "Kindle版",
  "Title": "僕の部屋がダンジョンの休憩所になってしまった件 放課後の異世界冒険部",
  "Price": 660,
  "Category": "ジャンル別,ライトノベル",
  "Points": 7
 },
 {
  "Asin": "B00NSA5MRK",
  "URL": "https://www.amazon.co.jp/dp/B00NSA5MRK?tag=99hatena-22&linkCode=ogi&th=1&psc=1",
  "ImageURL": "https://m.media-amazon.com/images/I/61LGjfJTIkL.jpg",
  "Publisher": "竹書房",
  "Contributor": "斎王ことり(著)",
  "Booktype": "Kindle版",
  "Title": "寵愛のエデン　花嫁は黒伯爵の甘い生け贄 (蜜猫文庫)",
  "Price": 363,
  "Category": "ジャンル別,ライトノベル",
  "Points": 4
 },
 {
  "Asin": "B01LWXCDZZ",
  "URL": "https://www.amazon.co.jp/dp/B01LWXCDZZ?tag=99hatena-22&linkCode=ogi&th=1&psc=1",
  "ImageURL": "https://m.media-amazon.com/images/I/61aTj9nuVtL.jpg",
  "Publisher": "竹書房",
  "Contributor": "藍杜雫(著)",
  "Booktype": "Kindle版",
  "Title": "聖爵猊下の新妻は離婚しません！ (蜜猫文庫)",
  "Price": 352,
  "Category": "ジャンル別,ライトノベル",
  "Points": 4
 },
 {
  "Asin": "B01D34LD4G",
  "URL": "https://www.amazon.co.jp/dp/B01D34LD4G?tag=99hatena-22&linkCode=ogi&th=1&psc=1",
  "ImageURL": "https://m.media-amazon.com/images/I/51WesvPeHoL.jpg",
  "Publisher": "竹書房",
  "Contributor": "ひらび久美(著)",
  "Booktype": "Kindle版",
  "Title": "恋愛遺伝子欠乏症 特効薬は御曹司！？ (蜜夢文庫)",
  "Price": 363,
  "Category": "ジャンル別,ライトノベル",
  "Points": 4
 },
 {
  "Asin": "B00V31CDXC",
  "URL": "https://www.amazon.co.jp/dp/B00V31CDXC?tag=99hatena-22&linkCode=ogi&th=1&psc=1",
  "ImageURL": "https://m.media-amazon.com/images/I/61b4kGYaroL.jpg",
  "Publisher": "竹書房",
  "Contributor": "すずね凜(著)",
  "Booktype": "Kindle版",
  "Title": "溺愛花嫁　朝に濡れ夜に乱れ (蜜猫文庫)",
  "Price": 352,
  "Category": "ジャンル別,ライトノベル",
  "Points": 4
 },
 {
  "Asin": "B084SCQ89Z",
  "URL": "https://www.amazon.co.jp/dp/B084SCQ89Z?tag=99hatena-22&linkCode=ogi&th=1&psc=1",
  "ImageURL": "https://m.media-amazon.com/images/I/51Xwj2gDe2L.jpg",
  "Publisher": "竹書房",
  "Contributor": "ひらび久美(著)",
  "Booktype": "Kindle版",
  "Title": "辛口な上司ですが、プライベートは極甘です。ただし、私、限定で！ (蜜夢文庫)",
  "Price": 440,
  "Category": "ジャンル別,ライトノベル",
  "Points": 4
 },
 {
  "Asin": "B079XXLCLT",
  "URL": "https://www.amazon.co.jp/dp/B079XXLCLT?tag=99hatena-22&linkCode=ogi&th=1&psc=1",
  "ImageURL": "https://m.media-amazon.com/images/I/6176kyFxx7L.jpg",
  "Publisher": "竹書房",
  "Contributor": "すずね凜(著)",
  "Booktype": "Kindle版",
  "Title": "ママになっても溺愛されてます 孤独な侯爵と没落令嬢のマリッジロマンス (蜜猫文庫)",
  "Price": 402,
  "Category": "ジャンル別,ライトノベル",
  "Points": 4
 },
 {
  "Asin": "B07XLRGG48",
  "URL": "https://www.amazon.co.jp/dp/B07XLRGG48?tag=99hatena-22&linkCode=ogi&th=1&psc=1",
  "ImageURL": "https://m.media-amazon.com/images/I/512uMqfWugL.jpg",
  "Publisher": "竹書房",
  "Contributor": "御影りさ(著)",
  "Booktype": "Kindle版",
  "Title": "次期国王の決め手は繁殖力だそうです (ムーンドロップス)",
  "Price": 440,
  "Category": "ジャンル別,ライトノベル",
  "Points": 4
 },
 {
  "Asin": "B01JGCEQAC",
  "URL": "https://www.amazon.co.jp/dp/B01JGCEQAC?tag=99hatena-22&linkCode=ogi&th=1&psc=1",
  "ImageURL": "https://m.media-amazon.com/images/I/6170rG6etBL.jpg",
  "Publisher": "竹書房",
  "Contributor": "如月(著)",
  "Booktype": "Kindle版",
  "Title": "溺愛志願　恋人は檻の中 (蜜猫文庫)",
  "Price": 352,
  "Category": "ジャンル別,ライトノベル",
  "Points": 4
 },
 {
  "Asin": "B07M7T3WYD",
  "URL": "https://www.amazon.co.jp/dp/B07M7T3WYD?tag=99hatena-22&linkCode=ogi&th=1&psc=1",
  "ImageURL": "https://m.media-amazon.com/images/I/61IkmJCQyLL.jpg",
  "Publisher": "竹書房",
  "Contributor": "すずね凜(著)",
  "Booktype": "Kindle版",
  "Title": "甘く淫らな婚活指導 (蜜猫文庫)",
  "Price": 413,
  "Category": "ジャンル別,ライトノベル",
  "Points": 4
 },
 {
  "Asin": "B07GF3SGNF",
  "URL": "https://www.amazon.co.jp/dp/B07GF3SGNF?tag=99hatena-22&linkCode=ogi&th=1&psc=1",
  "ImageURL": "https://m.media-amazon.com/images/I/512OjyqQK6L.jpg",
  "Publisher": "竹書房",
  "Contributor": "御子柴くれは(著)",
  "Booktype": "Kindle版",
  "Title": "セレブ社長と偽装結婚　箱入り姫は甘く疼いて！？ (蜜夢文庫)",
  "Price": 413,
  "Category": "ジャンル別,ライトノベル",
  "Points": 4
 },
 {
  "Asin": "B076LN6KDG",
  "URL": "https://www.amazon.co.jp/dp/B076LN6KDG?tag=99hatena-22&linkCode=ogi&th=1&psc=1",
  "ImageURL": "https://m.media-amazon.com/images/I/61yUigEoRwL.jpg",
  "Publisher": "竹書房",
  "Contributor": "真宮奏(著)",
  "Booktype": "Kindle版",
  "Title": "狐姫の身代わり婚 ～初恋王子はとんだケダモノ！？～ (ムーンドロップス)",
  "Price": 660,
  "Category": "ジャンル別,ライトノベル",
  "Points": 7
 },
 {
  "Asin": "B00XTRIP0I",
  "URL": "https://www.amazon.co.jp/dp/B00XTRIP0I?tag=99hatena-22&linkCode=ogi&th=1&psc=1",
  "ImageURL": "https://m.media-amazon.com/images/I/61MWkTRvw7L.jpg",
  "Publisher": "竹書房",
  "Contributor": "水嶋凜(著)",
  "Booktype": "Kindle版",
  "Title": "甘い束縛　軍人侯爵の淫戯 (蜜猫文庫)",
  "Price": 352,
  "Category": "ジャンル別,ライトノベル",
  "Points": 4
 },
 {
  "Asin": "B07QM5C6B1",
  "URL": "https://www.amazon.co.jp/dp/B07QM5C6B1?tag=99hatena-22&linkCode=ogi&th=1&psc=1",
  "ImageURL": "https://m.media-amazon.com/images/I/51E535XUtJL.jpg",
  "Publisher": "竹書房",
  "Contributor": "ぐるもり(著)",
  "Booktype": "Kindle版",
  "Title": "指名Ｎｏ．1のトップスタイリストは私の髪を愛撫する (蜜夢文庫)",
  "Price": 440,
  "Category": "ジャンル別,ライトノベル",
  "Points": 4
 },
 {
  "Asin": "B06XKVHTZ3",
  "URL": "https://www.amazon.co.jp/dp/B06XKVHTZ3?tag=99hatena-22&linkCode=ogi&th=1&psc=1",
  "ImageURL": "https://m.media-amazon.com/images/I/61E8qIqdcbL.jpg",
  "Publisher": "竹書房",
  "Contributor": "西條六花(著)",
  "Booktype": "Kindle版",
  "Title": "ピアニストの執愛　その指に囚われて (蜜夢文庫)",
  "Price": 385,
  "Category": "ジャンル別,ライトノベル",
  "Points": 4
 },
 {
  "Asin": "B0792VH1KT",
  "URL": "https://www.amazon.co.jp/dp/B0792VH1KT?tag=99hatena-22&linkCode=ogi&th=1&psc=1",
  "ImageURL": "https://m.media-amazon.com/images/I/516Y4ZcW8XL.jpg",
  "Publisher": "竹書房",
  "Contributor": "朝来みゆか(著)",
  "Booktype": "Kindle版",
  "Title": "旦那様はボディガード　偽装結婚したら、本気の恋に落ちました (蜜夢文庫)",
  "Price": 413,
  "Category": "ジャンル別,ライトノベル",
  "Points": 4
 },
 {
  "Asin": "B01N7V3A8T",
  "URL": "https://www.amazon.co.jp/dp/B01N7V3A8T?tag=99hatena-22&linkCode=ogi&th=1&psc=1",
  "ImageURL": "https://m.media-amazon.com/images/I/61aeXX2GB4L.jpg",
  "Publisher": "竹書房",
  "Contributor": "芹名りせ(著)",
  "Booktype": "Kindle版",
  "Title": "日陰者の王女ですが皇帝陛下に略奪溺愛されてます (蜜猫文庫)",
  "Price": 385,
  "Category": "ジャンル別,ライトノベル",
  "Points": 4
 },
 {
  "Asin": "B00XTRIOVI",
  "URL": "https://www.amazon.co.jp/dp/B00XTRIOVI?tag=99hatena-22&linkCode=ogi&th=1&psc=1",
  "ImageURL": "https://m.media-amazon.com/images/I/61SGrkbUiZL.jpg",
  "Publisher": "竹書房",
  "Contributor": "御堂志生(著)",
  "Booktype": "Kindle版",
  "Title": "惑愛　乙女は蜜夜に濡れる (蜜猫文庫)",
  "Price": 352,
  "Category": "ジャンル別,ライトノベル",
  "Points": 4
 },
 {
  "Asin": "B01AUMBT6Q",
  "URL": "https://www.amazon.co.jp/dp/B01AUMBT6Q?tag=99hatena-22&linkCode=ogi&th=1&psc=1",
  "ImageURL": "https://m.media-amazon.com/images/I/61V8XgangOL.jpg",
  "Publisher": "竹書房",
  "Contributor": "高田ちさき(著)",
  "Booktype": "Kindle版",
  "Title": "恋文ラビリンス 担当編集は初恋の彼！？ (蜜夢文庫)",
  "Price": 363,
  "Category": "ジャンル別,ライトノベル",
  "Points": 4
 },
 {
  "Asin": "B07BZ91BPY",
  "URL": "https://www.amazon.co.jp/dp/B07BZ91BPY?tag=99hatena-22&linkCode=ogi&th=1&psc=1",
  "ImageURL": "https://m.media-amazon.com/images/I/61V8wBal-EL.jpg",
  "Publisher": "竹書房",
  "Contributor": "青砥あか(著)",
  "Booktype": "Kindle版",
  "Title": "２９歳独身レディが、年下軍人から結婚をゴリ押しされて困ってます。 (ムーンドロップス)",
  "Price": 660,
  "Category": "ジャンル別,ライトノベル",
  "Points": 7
 },
 {
  "Asin": "B01B1G8CEC",
  "URL": "https://www.amazon.co.jp/dp/B01B1G8CEC?tag=99hatena-22&linkCode=ogi&th=1&psc=1",
  "ImageURL": "https://m.media-amazon.com/images/I/61SlKkcDSGL.jpg",
  "Publisher": "竹書房",
  "Contributor": "白石まと(著)",
  "Booktype": "Kindle版",
  "Title": "王太子殿下と秘密の貴婦人 (蜜猫文庫)",
  "Price": 352,
  "Category": "ジャンル別,ライトノベル",
  "Points": 4
 },
 {
  "Asin": "B01JGCEQ4I",
  "URL": "https://www.amazon.co.jp/dp/B01JGCEQ4I?tag=99hatena-22&linkCode=ogi&th=1&psc=1",
  "ImageURL": "https://m.media-amazon.com/images/I/61qsQgRZEBL.jpg",
  "Publisher": "竹書房",
  "Contributor": "七福さゆり(著)",
  "Booktype": "Kindle版",
  "Title": "王子様との危険な遊戯 (蜜猫文庫)",
  "Price": 352,
  "Category": "ジャンル別,ライトノベル",
  "Points": 4
 },
 {
  "Asin": "B07D4CFNZ7",
  "URL": "https://www.amazon.co.jp/dp/B07D4CFNZ7?tag=99hatena-22&linkCode=ogi&th=1&psc=1",
  "ImageURL": "https://m.media-amazon.com/images/I/61ubNy6PpVL.jpg",
  "Publisher": "竹書房",
  "Contributor": "鳴海澪(著)",
  "Booktype": "Kindle版",
  "Title": "俺様御曹司に愛されすぎ　干物なリケジョが潤って！？ (蜜夢文庫)",
  "Price": 413,
  "Category": "ジャンル別,ライトノベル",
  "Points": 4
 },
 {
  "Asin": "B082PSLG3P",
  "URL": "https://www.amazon.co.jp/dp/B082PSLG3P?tag=99hatena-22&linkCode=ogi&th=1&psc=1",
  "ImageURL": "https://m.media-amazon.com/images/I/51iaRhOhanL.jpg",
  "Publisher": "竹書房",
  "Contributor": "栗谷あずみ(著)",
  "Booktype": "Kindle版",
  "Title": "あまとろクルーズ　腹黒パティシエは猫かぶり上司を淫らに躾ける (蜜夢文庫)",
  "Price": 440,
  "Category": "ジャンル別,ライトノベル",
  "Points": 4
 },
 {
  "Asin": "B0792VJ375",
  "URL": "https://www.amazon.co.jp/dp/B0792VJ375?tag=99hatena-22&linkCode=ogi&th=1&psc=1",
  "ImageURL": "https://m.media-amazon.com/images/I/61wh96YVUEL.jpg",
  "Publisher": "竹書房",
  "Contributor": "麻生ミカリ(著)",
  "Booktype": "Kindle版",
  "Title": "若き皇帝は虜の新妻を溺愛する (蜜猫文庫)",
  "Price": 402,
  "Category": "ジャンル別,ライトノベル",
  "Points": 4
 },
 {
  "Asin": "B01LXIC9HC",
  "URL": "https://www.amazon.co.jp/dp/B01LXIC9HC?tag=99hatena-22&linkCode=ogi&th=1&psc=1",
  "ImageURL": "https://m.media-amazon.com/images/I/512dM91fvvL.jpg",
  "Publisher": "竹書房",
  "Contributor": "御堂志生(著)",
  "Booktype": "Kindle版",
  "Title": "償いは蜜の味　Ｓ系パイロットの淫らなおしおき (蜜夢文庫)",
  "Price": 363,
  "Category": "ジャンル別,ライトノベル",
  "Points": 4
 },
 {
  "Asin": "B07T5L27HB",
  "URL": "https://www.amazon.co.jp/dp/B07T5L27HB?tag=99hatena-22&linkCode=ogi&th=1&psc=1",
  "ImageURL": "https://m.media-amazon.com/images/I/51cFqYm5raL.jpg",
  "Publisher": "竹書房",
  "Contributor": "西條六花(著)",
  "Booktype": "Kindle版",
  "Title": "無愛想ドクターの時間外診療　甘い刺激に乱されています (蜜夢文庫)",
  "Price": 440,
  "Category": "ジャンル別,ライトノベル",
  "Points": 4
 },
 {
  "Asin": "B07NPLZDCX",
  "URL": "https://www.amazon.co.jp/dp/B07NPLZDCX?tag=99hatena-22&linkCode=ogi&th=1&psc=1",
  "ImageURL": "https://m.media-amazon.com/images/I/51iRbchm3DL.jpg",
  "Publisher": "竹書房",
  "Contributor": "高田ちさき(著)",
  "Booktype": "Kindle版",
  "Title": "ラブ・ロンダリング　年下エリートは狙った獲物を甘く堕とす (蜜夢文庫)",
  "Price": 440,
  "Category": "ジャンル別,ライトノベル",
  "Points": 4
 },
 {
  "Asin": "B07JC9RL7C",
  "URL": "https://www.amazon.co.jp/dp/B07JC9RL7C?tag=99hatena-22&linkCode=ogi&th=1&psc=1",
  "ImageURL": "https://m.media-amazon.com/images/I/51DnnWxHW8L.jpg",
  "Publisher": "竹書房",
  "Contributor": "水城のあ(著)",
  "Booktype": "Kindle版",
  "Title": "Ｓ系厨房男子に餌付け調教されました (蜜夢文庫)",
  "Price": 413,
  "Category": "ジャンル別,ライトノベル",
  "Points": 4
 },
 {
  "Asin": "B075R37FBQ",
  "URL": "https://www.amazon.co.jp/dp/B075R37FBQ?tag=99hatena-22&linkCode=ogi&th=1&psc=1",
  "ImageURL": "https://m.media-amazon.com/images/I/61wpVsYvTQL.jpg",
  "Publisher": "竹書房",
  "Contributor": "粟生慧(著)",
  "Booktype": "Kindle版",
  "Title": "人質王女が皇帝陛下といちゃらぶ溺愛婚ですかっ！？ (蜜猫文庫)",
  "Price": 402,
  "Category": "ジャンル別,ライトノベル",
  "Points": 4
 },
 {
  "Asin": "B01M041BKB",
  "URL": "https://www.amazon.co.jp/dp/B01M041BKB?tag=99hatena-22&linkCode=ogi&th=1&psc=1",
  "ImageURL": "https://m.media-amazon.com/images/I/513GJEV8wJL.jpg",
  "Publisher": "竹書房",
  "Contributor": "水城のあ(著)",
  "Booktype": "Kindle版",
  "Title": "あなたのシンデレラ 若社長の強引なエスコート (蜜夢文庫)",
  "Price": 363,
  "Category": "ジャンル別,ライトノベル",
  "Points": 4
 },
 {
  "Asin": "B07FNGHX8Q",
  "URL": "https://www.amazon.co.jp/dp/B07FNGHX8Q?tag=99hatena-22&linkCode=ogi&th=1&psc=1",
  "ImageURL": "https://m.media-amazon.com/images/I/51neC3-q2BL.jpg",
  "Publisher": "竹書房",
  "Contributor": "西條六花(著)",
  "Booktype": "Kindle版",
  "Title": "年下幼なじみと二度目の初体験？　逃げられないほど愛されています (蜜夢文庫)",
  "Price": 413,
  "Category": "ジャンル別,ライトノベル",
  "Points": 4
 },
 {
  "Asin": "B00NSA5MOI",
  "URL": "https://www.amazon.co.jp/dp/B00NSA5MOI?tag=99hatena-22&linkCode=ogi&th=1&psc=1",
  "ImageURL": "https://m.media-amazon.com/images/I/616b+KH8KIL.jpg",
  "Publisher": "竹書房",
  "Contributor": "みかづき紅月(著)",
  "Booktype": "Kindle版",
  "Title": "石油王の略奪　愛執の檻 (蜜猫文庫)",
  "Price": 352,
  "Category": "ジャンル別,ライトノベル",
  "Points": 4
 },
 {
  "Asin": "B01N95EPIM",
  "URL": "https://www.amazon.co.jp/dp/B01N95EPIM?tag=99hatena-22&linkCode=ogi&th=1&psc=1",
  "ImageURL": "https://m.media-amazon.com/images/I/51-Tq6+tyUL.jpg",
  "Publisher": "竹書房",
  "Contributor": "高田ちさき(著)",
  "Booktype": "Kindle版",
  "Title": "あなたの言葉に溺れたい 恋愛小説家と淫らな読書会 (蜜夢文庫)",
  "Price": 374,
  "Category": "ジャンル別,ライトノベル",
  "Points": 4
 },
 {
  "Asin": "B01JGCEQPM",
  "URL": "https://www.amazon.co.jp/dp/B01JGCEQPM?tag=99hatena-22&linkCode=ogi&th=1&psc=1",
  "ImageURL": "https://m.media-amazon.com/images/I/61ufR0UTO-L.jpg",
  "Publisher": "竹書房",
  "Contributor": "森本あき(著)",
  "Booktype": "Kindle版",
  "Title": "買われた新妻は溺愛される (蜜猫文庫)",
  "Price": 363,
  "Category": "ジャンル別,ライトノベル",
  "Points": 4
 },
 {
  "Asin": "B017R0TVC8",
  "URL": "https://www.amazon.co.jp/dp/B017R0TVC8?tag=99hatena-22&linkCode=ogi&th=1&psc=1",
  "ImageURL": "https://m.media-amazon.com/images/I/61p2iwF74pL.jpg",
  "Publisher": "竹書房",
  "Contributor": "夜織もか(著)",
  "Booktype": "Kindle版",
  "Title": "甘い蜜の牢獄 (蜜猫文庫)",
  "Price": 352,
  "Category": "ジャンル別,ライトノベル",
  "Points": 4
 },
 {
  "Asin": "B017R0TVBE",
  "URL": "https://www.amazon.co.jp/dp/B017R0TVBE?tag=99hatena-22&linkCode=ogi&th=1&psc=1",
  "ImageURL": "https://m.media-amazon.com/images/I/61yCPs-dolL.jpg",
  "Publisher": "竹書房",
  "Contributor": "外岡キリア(著)",
  "Booktype": "Kindle版",
  "Title": "屈辱の寵愛 皇帝に奪われた王女の純潔 (蜜猫文庫)",
  "Price": 352,
  "Category": "ジャンル別,ライトノベル",
  "Points": 4
 },
 {
  "Asin": "B019C8S2S2",
  "URL": "https://www.amazon.co.jp/dp/B019C8S2S2?tag=99hatena-22&linkCode=ogi&th=1&psc=1",
  "ImageURL": "https://m.media-amazon.com/images/I/51XJWkplOzL.jpg",
  "Publisher": "竹書房",
  "Contributor": "鳴海澪(著)",
  "Booktype": "Kindle版",
  "Title": "赤い靴のシンデレラ　身代わり花嫁の恋 (蜜夢文庫)",
  "Price": 349,
  "Category": "ジャンル別,ライトノベル",
  "Points": 3
 },
 {
  "Asin": "B01MTACEZ8",
  "URL": "https://www.amazon.co.jp/dp/B01MTACEZ8?tag=99hatena-22&linkCode=ogi&th=1&psc=1",
  "ImageURL": "https://m.media-amazon.com/images/I/51B3IrqMN4L.jpg",
  "Publisher": "竹書房",
  "Contributor": "鳴海澪(著)",
  "Booktype": "Kindle版",
  "Title": "溺愛コンチェルト　御曹司は花嫁を束縛する (蜜夢文庫)",
  "Price": 385,
  "Category": "ジャンル別,ライトノベル",
  "Points": 4
 },
 {
  "Asin": "B0151GZHN2",
  "URL": "https://www.amazon.co.jp/dp/B0151GZHN2?tag=99hatena-22&linkCode=ogi&th=1&psc=1",
  "ImageURL": "https://m.media-amazon.com/images/I/61Tef5stjrL.jpg",
  "Publisher": "竹書房",
  "Contributor": "森本あき(著)",
  "Booktype": "Kindle版",
  "Title": "身代わり花嫁の災難 (蜜猫文庫)",
  "Price": 352,
  "Category": "ジャンル別,ライトノベル",
  "Points": 4
 },
 {
  "Asin": "B07FFTQH6K",
  "URL": "https://www.amazon.co.jp/dp/B07FFTQH6K?tag=99hatena-22&linkCode=ogi&th=1&psc=1",
  "ImageURL": "https://m.media-amazon.com/images/I/51BfX1FmcML.jpg",
  "Publisher": "竹書房",
  "Contributor": "上主沙夜(著)",
  "Booktype": "Kindle版",
  "Title": "不埒な海竜王に怒濤の勢いで溺愛されています！　スパダリ神に美味しくいただかれた生贄花嫁！？ (蜜猫ｎｏｖｅｌｓ)",
  "Price": 660,
  "Category": "ジャンル別,ライトノベル",
  "Points": 7
 },
 {
  "Asin": "B0151GZIO0",
  "URL": "https://www.amazon.co.jp/dp/B0151GZIO0?tag=99hatena-22&linkCode=ogi&th=1&psc=1",
  "ImageURL": "https://m.media-amazon.com/images/I/61IRZRBiMNL.jpg",
  "Publisher": "竹書房",
  "Contributor": "麻生ミカリ(著)",
  "Booktype": "Kindle版",
  "Title": "トリニティマリッジ 愛されすぎた花嫁姫 (蜜猫文庫)",
  "Price": 352,
  "Category": "ジャンル別,ライトノベル",
  "Points": 4
 },
 {
  "Asin": "B01FVH2QQC",
  "URL": "https://www.amazon.co.jp/dp/B01FVH2QQC?tag=99hatena-22&linkCode=ogi&th=1&psc=1",
  "ImageURL": "https://m.media-amazon.com/images/I/61Bxs2EDooL.jpg",
  "Publisher": "竹書房",
  "Contributor": "栗谷あずみ(著)",
  "Booktype": "Kindle版",
  "Title": "楽園で恋をする ホテル御曹司の甘い求愛 (蜜夢文庫)",
  "Price": 363,
  "Category": "ジャンル別,ライトノベル",
  "Points": 4
 },
 {
  "Asin": "B07H9RYCL1",
  "URL": "https://www.amazon.co.jp/dp/B07H9RYCL1?tag=99hatena-22&linkCode=ogi&th=1&psc=1",
  "ImageURL": "https://m.media-amazon.com/images/I/617Ais1G-WL.jpg",
  "Publisher": "竹書房",
  "Contributor": "森本あき(著)",
  "Booktype": "Kindle版",
  "Title": "富豪伯爵に買われましたが甘甘溺愛されてます (蜜猫文庫)",
  "Price": 402,
  "Category": "ジャンル別,ライトノベル",
  "Points": 4
 },
 {
  "Asin": "B0792V68K5",
  "URL": "https://www.amazon.co.jp/dp/B0792V68K5?tag=99hatena-22&linkCode=ogi&th=1&psc=1",
  "ImageURL": "https://m.media-amazon.com/images/I/51wQ8cgqdYL.jpg",
  "Publisher": "竹書房",
  "Contributor": "水城のあ(著)",
  "Booktype": "Kindle版",
  "Title": "露天風呂で初恋の幼なじみと再会して、求婚されちゃいました！！ (蜜夢文庫)",
  "Price": 413,
  "Category": "ジャンル別,ライトノベル",
  "Points": 4
 },
 {
  "Asin": "B01JGCEQJS",
  "URL": "https://www.amazon.co.jp/dp/B01JGCEQJS?tag=99hatena-22&linkCode=ogi&th=1&psc=1",
  "ImageURL": "https://m.media-amazon.com/images/I/61CxNM-x2sL.jpg",
  "Publisher": "竹書房",
  "Contributor": "すずね凜(著)",
  "Booktype": "Kindle版",
  "Title": "新婚溺愛物語 契約の新妻は甘く蕩けて (蜜猫文庫)",
  "Price": 352,
  "Category": "ジャンル別,ライトノベル",
  "Points": 4
 },
 {
  "Asin": "B07MJRVMCC",
  "URL": "https://www.amazon.co.jp/dp/B07MJRVMCC?tag=99hatena-22&linkCode=ogi&th=1&psc=1",
  "ImageURL": "https://m.media-amazon.com/images/I/51CEu23j07L.jpg",
  "Publisher": "竹書房",
  "Contributor": "天ヶ森雀(著)",
  "Booktype": "Kindle版",
  "Title": "気高き花嫁は白銀王の腕で愛欲に震える (ムーンドロップス)",
  "Price": 880,
  "Category": "ジャンル別,ライトノベル",
  "Points": 9
 },
 {
  "Asin": "B07289JQFR",
  "URL": "https://www.amazon.co.jp/dp/B07289JQFR?tag=99hatena-22&linkCode=ogi&th=1&psc=1",
  "ImageURL": "https://m.media-amazon.com/images/I/5113i984-kL.jpg",
  "Publisher": "竹書房",
  "Contributor": "深雪まゆ(著)",
  "Booktype": "Kindle版",
  "Title": "社内恋愛禁止 ～あなたと秘密のランジェリー～ (蜜夢文庫)",
  "Price": 385,
  "Category": "ジャンル別,ライトノベル",
  "Points": 4
 },
 {
  "Asin": "B079PXPWKT",
  "URL": "https://www.amazon.co.jp/dp/B079PXPWKT?tag=99hatena-22&linkCode=ogi&th=1&psc=1",
  "ImageURL": "https://m.media-amazon.com/images/I/61z8QKZVHLL.jpg",
  "Publisher": "竹書房",
  "Contributor": "吹雪歌音(著)",
  "Booktype": "Kindle版",
  "Title": "舞姫に転生したＯＬは砂漠の王に貪り愛される (ムーンドロップス)",
  "Price": 660,
  "Category": "ジャンル別,ライトノベル",
  "Points": 7
 },
 {
  "Asin": "B019C8S2PU",
  "URL": "https://www.amazon.co.jp/dp/B019C8S2PU?tag=99hatena-22&linkCode=ogi&th=1&psc=1",
  "ImageURL": "https://m.media-amazon.com/images/I/61yhxXWBkiL.jpg",
  "Publisher": "竹書房",
  "Contributor": "玉紀直(著)",
  "Booktype": "Kindle版",
  "Title": "オトナの恋を教えてあげる　ドＳ執事の甘い調教 (蜜夢文庫)",
  "Price": 352,
  "Category": "ジャンル別,ライトノベル",
  "Points": 4
 },
 {
  "Asin": "B01MFCM4ZJ",
  "URL": "https://www.amazon.co.jp/dp/B01MFCM4ZJ?tag=99hatena-22&linkCode=ogi&th=1&psc=1",
  "ImageURL": "https://m.media-amazon.com/images/I/61XQ+3BGaJL.jpg",
  "Publisher": "竹書房",
  "Contributor": "小出みき(著)",
  "Booktype": "Kindle版",
  "Title": "傲慢貴族の惑溺愛 (蜜猫文庫)",
  "Price": 385,
  "Category": "ジャンル別,ライトノベル",
  "Points": 4
 },
 {
  "Asin": "B01MG55CQO",
  "URL": "https://www.amazon.co.jp/dp/B01MG55CQO?tag=99hatena-22&linkCode=ogi&th=1&psc=1",
  "ImageURL": "https://m.media-amazon.com/images/I/61X+1qcNRrL.jpg",
  "Publisher": "竹書房",
  "Contributor": "夜織もか(著)",
  "Booktype": "Kindle版",
  "Title": "軍人皇帝は新妻をかわいがるのに忙しい (蜜猫文庫)",
  "Price": 382,
  "Category": "ジャンル別,ライトノベル",
  "Points": 4
 },
 {
  "Asin": "B07DVLTGV1",
  "URL": "https://www.amazon.co.jp/dp/B07DVLTGV1?tag=99hatena-22&linkCode=ogi&th=1&psc=1",
  "ImageURL": "https://m.media-amazon.com/images/I/61j7AX-rbwL.jpg",
  "Publisher": "竹書房",
  "Contributor": "上主沙夜(著)",
  "Booktype": "Kindle版",
  "Title": "皇帝陛下の専属耳かき係を仰せつかりました。　年の差婚は溺愛の始まり！？ (蜜猫文庫)",
  "Price": 397,
  "Category": "ジャンル別,ライトノベル",
  "Points": 4
 },
 {
  "Asin": "B00PQDJM3M",
  "URL": "https://www.amazon.co.jp/dp/B00PQDJM3M?tag=99hatena-22&linkCode=ogi&th=1&psc=1",
  "ImageURL": "https://m.media-amazon.com/images/I/61fBVx7hJ4L.jpg",
  "Publisher": "竹書房",
  "Contributor": "夜織もか(著)",
  "Booktype": "Kindle版",
  "Title": "鳥籠の中の愉悦　貴公子の指先に溺れて (蜜猫文庫)",
  "Price": 352,
  "Category": "ジャンル別,ライトノベル",
  "Points": 4
 },
 {
  "Asin": "B079PVPHY2",
  "URL": "https://www.amazon.co.jp/dp/B079PVPHY2?tag=99hatena-22&linkCode=ogi&th=1&psc=1",
  "ImageURL": "https://m.media-amazon.com/images/I/61HB3vKuSPL.jpg",
  "Publisher": "竹書房",
  "Contributor": "天ヶ森雀(著)",
  "Booktype": "Kindle版",
  "Title": "魔王の娘と白鳥の騎士　罠にかけるつもりが食べられちゃいました (ムーンドロップス)",
  "Price": 715,
  "Category": "ジャンル別,ライトノベル",
  "Points": 7
 },
 {
  "Asin": "B01IR01U7Q",
  "URL": "https://www.amazon.co.jp/dp/B01IR01U7Q?tag=99hatena-22&linkCode=ogi&th=1&psc=1",
  "ImageURL": "https://m.media-amazon.com/images/I/51HMwE6Fv8L.jpg",
  "Publisher": "竹書房",
  "Contributor": "真坂たま(著)",
  "Booktype": "Kindle版",
  "Title": "ワケあり物件 契約中 ～カリスマ占い師と不機嫌な恋人 (蜜夢文庫)",
  "Price": 363,
  "Category": "ジャンル別,ライトノベル",
  "Points": 4
 },
 {
  "Asin": "B01AUMBT84",
  "URL": "https://www.amazon.co.jp/dp/B01AUMBT84?tag=99hatena-22&linkCode=ogi&th=1&psc=1",
  "ImageURL": "https://m.media-amazon.com/images/I/51kZuMwOjFL.jpg",
  "Publisher": "竹書房",
  "Contributor": "日野さつき(著)",
  "Booktype": "Kindle版",
  "Title": "強引執着溺愛ダーリン あきらめの悪い御曹司 (蜜夢文庫)",
  "Price": 363,
  "Category": "ジャンル別,ライトノベル",
  "Points": 4
 },
 {
  "Asin": "B0151GZHQE",
  "URL": "https://www.amazon.co.jp/dp/B0151GZHQE?tag=99hatena-22&linkCode=ogi&th=1&psc=1",
  "ImageURL": "https://m.media-amazon.com/images/I/61LJwTeWqJL.jpg",
  "Publisher": "竹書房",
  "Contributor": "みかづき紅月(著)",
  "Booktype": "Kindle版",
  "Title": "執愛遊戯　甘い支配に溺れて (蜜猫文庫)",
  "Price": 352,
  "Category": "ジャンル別,ライトノベル",
  "Points": 4
 },
 {
  "Asin": "B0767BW61L",
  "URL": "https://www.amazon.co.jp/dp/B0767BW61L?tag=99hatena-22&linkCode=ogi&th=1&psc=1",
  "ImageURL": "https://m.media-amazon.com/images/I/618LmbuXUDL.jpg",
  "Publisher": "竹書房",
  "Contributor": "みかづき紅月(著)",
  "Booktype": "Kindle版",
  "Title": "平凡なOLがアリスの世界にトリップしたら帽子屋の紳士に溺愛されました。 (蜜猫ｎｏｖｅｌｓ)",
  "Price": 660,
  "Category": "ジャンル別,ライトノベル",
  "Points": 7
 },
 {
  "Asin": "B01MY9IF04",
  "URL": "https://www.amazon.co.jp/dp/B01MY9IF04?tag=99hatena-22&linkCode=ogi&th=1&psc=1",
  "ImageURL": "https://m.media-amazon.com/images/I/51OqE2UeKLL.jpg",
  "Publisher": "竹書房",
  "Contributor": "ひらび久美(著)",
  "Booktype": "Kindle版",
  "Title": "フォンダンショコラ男子は甘く蕩ける (蜜夢文庫)",
  "Price": 385,
  "Category": "ジャンル別,ライトノベル",
  "Points": 4
 },
 {
  "Asin": "B07BJY6CX7",
  "URL": "https://www.amazon.co.jp/dp/B07BJY6CX7?tag=99hatena-22&linkCode=ogi&th=1&psc=1",
  "ImageURL": "https://m.media-amazon.com/images/I/51rFng7j1UL.jpg",
  "Publisher": "竹書房",
  "Contributor": "高田ちさき(著)",
  "Booktype": "Kindle版",
  "Title": "元教え子のホテルＣＥＯにスイートルームで溺愛されています。 (蜜夢文庫)",
  "Price": 413,
  "Category": "ジャンル別,ライトノベル",
  "Points": 4
 },
 {
  "Asin": "B01FVH2QMG",
  "URL": "https://www.amazon.co.jp/dp/B01FVH2QMG?tag=99hatena-22&linkCode=ogi&th=1&psc=1",
  "ImageURL": "https://m.media-amazon.com/images/I/61S5fCP8iGL.jpg",
  "Publisher": "竹書房",
  "Contributor": "冬野まゆ(著)",
  "Booktype": "Kindle版",
  "Title": "小鳩君ドット迷惑　押しかけ同居人は人気俳優！？ (蜜夢文庫)",
  "Price": 363,
  "Category": "ジャンル別,ライトノベル",
  "Points": 4
 },
 {
  "Asin": "B07BZK6D89",
  "URL": "https://www.amazon.co.jp/dp/B07BZK6D89?tag=99hatena-22&linkCode=ogi&th=1&psc=1",
  "ImageURL": "https://m.media-amazon.com/images/I/61H1vovH06L.jpg",
  "Publisher": "竹書房",
  "Contributor": "かほり(著)",
  "Booktype": "Kindle版",
  "Title": "魔界の貴公子と宮廷魔術師は、真紅の姫君を奪い合う～私のために戦うのはやめて！！ (ムーンドロップス)",
  "Price": 660,
  "Category": "ジャンル別,ライトノベル",
  "Points": 7
 },
 {
  "Asin": "B071GC4HF8",
  "URL": "https://www.amazon.co.jp/dp/B071GC4HF8?tag=99hatena-22&linkCode=ogi&th=1&psc=1",
  "ImageURL": "https://m.media-amazon.com/images/I/515sNMwDLDL.jpg",
  "Publisher": "竹書房",
  "Contributor": "笹原せつ(著)",
  "Booktype": "Kindle版",
  "Title": "十五年前のぼく",
  "Price": 361,
  "Category": "ジャンル別,ライトノベル",
  "Points": 4
 },
 {
  "Asin": "B00RF92MUA",
  "URL": "https://www.amazon.co.jp/dp/B00RF92MUA?tag=99hatena-22&linkCode=ogi&th=1&psc=1",
  "ImageURL": "https://m.media-amazon.com/images/I/61ZN901g6ZL.jpg",
  "Publisher": "竹書房",
  "Contributor": "砂月砂都子(著)",
  "Booktype": "Kindle版",
  "Title": "パニック・ラブ・ボックス (恋パラ☆えろらぶノベル)",
  "Price": 165,
  "Category": "ジャンル別,ライトノベル",
  "Points": 2
 }
]